MANIFEST.in
README.rst
setup.py
sketchduino/__init__.py
sketchduino/args.py
sketchduino/screen.py
sketchduino/template.py
sketchduino.egg-info/PKG-INFO
sketchduino.egg-info/SOURCES.txt
sketchduino.egg-info/dependency_links.txt
sketchduino.egg-info/entry_points.txt
sketchduino.egg-info/requires.txt
sketchduino.egg-info/top_level.txt