Metadata-Version: 1.0
Name: sketchduino
Version: 0.5.2
Summary:  Arduino Sketch Generator
Home-page: UNKNOWN
Author: Rodrigo Pinheiro Matias
Author-email: rodrigopmatias@gmail.com
License: Apache 2.0
Platform: GNU/Linux
